{
    "$10 per GB above package": "$10 per GB above package",
    "$1000 / month": "$1000 / mes",
    "$12.5 per GB above package": "$12.5 por GB paquete de arriba",
    "$5 per GB above package": "$5 per GB above package",
    "$500 / month": "$500 / month",
    "100 GB": "100 GB",
    "13.5 million": "13.5 milliones",
    "20,000 IPs": "20,000 IPs",
    "40 GB": "40 GB",
    "<span class=\"big\">Advanced</span> Residential": "<span class=\"big\">Avanzado</span> Residencial",
    "<span class=\"big\">Advanced</span> plans": "<span class=\"big\">Avanzado</span> plans",
    "<span class=\"big\">Basic</span> Residential": "<span class=\"big\">Basico</span> Residencial",
    "<span class=\"big\">Basic</span> Static": "<span class=\"big\">Basic</span> Static",
    "<span class=\"big\">Enterprise</span>": "<span class=\"big\">Corporacion</span>",
    "A proxy solution for business": "Una solucion proxy para negocios",
    "ASIA - PACIFIC": "ASIA - PACIFIC",
    "Ad Verification": "Verificaciones de anuncios",
    "Any city": "Cualquier ciudad",
    "Any country": "Any country",
    "Blog": "Blog",
    "Brand Protection": "Brand Protection",
    "Business proxy network": "Business proxy network",
    "Call:": "Llama:",
    "Cancellation &amp; refund": "Cancellation &amp; refund",
    "City": "City",
    "Compare Luminati with other solutions": "Compare Luminati with other solutions",
    "Concurrent sessions": "Conexiones Simultaneas",
    "Contact": "Contacto",
    "Contact us": "Contactanos",
    "Contact us to find out how Luminati can help your business harvest data reliably and anonymously, or start a free trial now": "Contactanos para descubrir como Luminati puede ayudar tu negocio colectar data de terceras parte de modo anonimo y comienza una prueba gratuita ahora",
    "Costly, requires development resources for failure handling": "Costly, requires development resources for failure handling",
    "Country": "Country",
    "Data Harvesting Reliability": "Confianza en la recolección de datos",
    "Define any city as your IP<br> location, so you can harvest local data": "Define any city as your IP<br> location, so you can harvest local data",
    "EUROPE": "EUROPE",
    "Email:": "Email:",
    "FAQ": "FAQ",
    "Fail rate": "Porcentaje de bloqueo",
    "Failure Rate": "Failure Rate",
    "Features": "Features",
    "Features &amp; Benefits": "Caracteristicas &amp; Beneficios",
    "For rates please <a href=\"mailto:sales@luminati.io\">contact us</a>": "For rates please <a href=\"mailto:sales@luminati.io\">contact us</a>",
    "Free Trial": "Prueba Gratuita",
    "Geo-Distribution": "Distribucion geografica",
    "Getting started": "Getting started",
    "Help job seekers and employers connect faster and more effectively": "Ayudar a los buscadores de empleo y empleadores conectarse de modo rápido y eficaz",
    "High, proxy IPs are frequently recognized and blocked": "High, proxy IPs are frequently recognized and blocked",
    "Highly reliable": "Altamente Fiable",
    "How it works": "How it works",
    "How to Use Luminati API â†’": "How to Use Luminati API â†’",
    "How to Use Luminati API →": "Como Utilizar el API de Lumianti",
    "IP Stickiness": "IP Stickiness",
    "IP switches": "Rotacion de IPs",
    "IPs around the world!": "IPs alrededor del mundo!",
    "IPs in 192 countries and nearly<br>every city": "IPs en 192 paises y casi<br>en cada ciudad",
    "In every city in the world": "En cada ciudad en el mundo",
    "Instant scaling": "Escalamiento Instantaneo",
    "Instant, millions of IPs immediately available": "Instant, millions of IPs immediately available",
    "Integration Time": "Tiempo de Integracion",
    "Limited number of countries and cities": "Limited number of countries and cities",
    "Long, requires configuration when scaling": "Largo, requiere de configuracion al crecer",
    "Low, minimal maintenance.<br> API includes management layer": "Baja, mantencion minima.<br> El API incluye un systema de managment",
    "Luminati is a service by <span class=\"lum-hola-logo\"></span>": "Luminati es un servicio por <span class=\"lum-hola-logo\"></span>",
    "Luminati vs. Traditional<br>Proxy Services": "Luminati vs. Traditional<br>Proxy Services",
    "Luminati's P2P proxy network consists of residential <br>IPs only, so you will not be blocked or misled": "La red proxy P2P de Luminati consiste solamente de <br>IPs residenciales, de modo que no sera bloquiado o engañado",
    "Luminati's residential IPs are never deceived, so your <br>data is always fresh and accurate": "Luminati's residential IPs are never deceived, so your <br>data is always fresh and accurate",
    "Medium": "Medium",
    "Millions of IPs": "Millones de IPs",
    "Minutes by integrating a code snippet": "Minutos para integrar un codigo snippet",
    "Monitor the web for proper use of customer's brands. Protect your Intellectual Property and trade marks": "Monitor the web for proper use of customer's brands. Protect your Intellectual Property and trade marks",
    "No": "No",
    "Number of IPs": "Numeros de IPs",
    "Premium": "Premium",
    "Pricing": "Pricing",
    "Privacy": "Privado",
    "Recognizable data center static IPs": "Centros de datos (Data Centers) reconocibles IPs estaticos",
    "Referral program": "Programa de referencia",
    "Reliable, as all IPs belong to residential devices": "Todos los IPs pertenecen a usuarios reales",
    "Report abuse": "Reporte de Abuso",
    "Residential": "Residencial",
    "Residential IPs": "IPs Recidenciales",
    "Residential IPs for fast and reliable massive scale web data extraction": "IPs residenciales para velocidad y confianza en crecimiento de coleccion de datos",
    "SOUTH AMERICA": "SOUTH AMERICA",
    "Scaling Up and Down": "Escalada arriba y abajo",
    "Self-Testing": "Self-Testing",
    "Send your HTTP/S requests to our \"Super proxies\", which will route<br>them to targets through millions of residential IPs.": "Envita tus pedidos HTTP/S a nuestros \"Super Proxies\", que seran reenviados <br>a los sitios por medio de de millones de IPs residenciales.",
    "Start free trial": "Start free trial",
    "Start immediately": "Comienza Inmediatamente",
    "Static": "Estatico",
    "Static IPs": "IPs estaticos",
    "Talent Sourcing": "Sourcing de Talento",
    "Test websites globally and view them locally": "Prueba sitios globalmente y miralos localmente",
    "The largest proxy network in the world,<br> so you can harvest data at super scale": "El proxy de red más grande en el mundo, <br> para que pueda colectar los datos a escala optima",
    "This site is owned and operated by<br> Hola Networks LTD.": "This site is owned and operated by<br> Hola Networks LTD.",
    "Thousands of IPs": "Miles de IPs",
    "Toggle navigation": "Toggle navigation",
    "Total Cost of Operation": "Total Cost of Operation",
    "Total available IPs": "Total available IPs",
    "Traditional Proxy Services": "Servicios proxy residenciales",
    "Type of IPs": "Tipos de IPs",
    "Typical integration takes 5 minutes by<br> integrating a simple <a href=\"#using\">code snippet</a>": "la integración típica tarda 5 minutos en <br> al integrar un simple fragmento de código <a href=\"#using\"> </a>",
    "Typically days of integration": "Dias de integracion",
    "USA & CANADA": "USA & CANADA",
    "Unlimited": "Ilimitado",
    "Unlimited IPs": "IPs Ilimitados",
    "Unlimited concurrent sessions": "Seciones paralelas ilimitadas",
    "Unlimited countries": "Paises Ilimitados",
    "Unrecognizable residential IPs": "Unrecognizable residential IPs",
    "Unreliable; websites identify data-center proxy IPs and send misleading data": "Inconfiable; sitios web indentifican centros de datos de proxis y les envian informacion erronea",
    "Verify ad integrity via millions of residential IP's. Eliminate misleading advertisement and backlinks": "Verify ad integrity via millions of residential IP's. Eliminate misleading advertisement and backlinks",
    "Very low": "Very low",
    "Very low, Residential IPs are rarely blocked": "Muy bajo, IPs residenciales son raramente bloquiados",
    "Web data harvesting:<br> anonymous, reliable, seamless": "La recolección de datos Web : <br> anónima , fiable , transparente >",
    "Why Luminati": "Porque Luminati",
    "Yes": "Si",
    "You pay only for the traffic you pass through the<br> network. You can use all of our IPs": "Se paga solo por el trafico que pasa por medio de <br> la red. Puede usar todos nuestros IPs."
}
