{
   "android" : {
      " Data saved" : " Data saved",
      " Hola Accelerated" : " Hola Accelerated",
      " Or " : " Or ",
      " Sample " : " Sample ",
      " Share it with anyone! If you don't have Hola yet, it should ask you to install - it's free!" : " Share it with anyone! If you don't have Hola yet, it should ask you to install - it's free!",
      " now with the Hola Unblocker!" : " now with the Hola Unblocker!",
      " with you! Just click here to add it to your Hola Unblocker:" : " with you! Just click here to add it to your Hola Unblocker:",
      "%1$s not supported" : "%1$s not supported",
      "(Type a brief description of the problem here)" : "(Type a brief description of the problem here)",
      "(Type your feedback here) " : "(Type your feedback here) ",
      "- Since you installed Hola -" : "- Since you installed Hola -",
      "About" : "About",
      "Accelerated" : "Accelerated",
      "Acceleration" : "Acceleration",
      "Accelerator" : "Accelerator",
      "Access " : "Access ",
      "Access apps and sites\ncensored in your country." : "Access apps and sites\ncensored in your country.",
      "Allow the installation of any app" : "Allow the installation of any app",
      "Always try root mode on starting hola" : "Always try root mode on starting hola",
      "Always use VPN mode" : "Always use VPN mode",
      "App conflict. Tap to resolve the problem" : "App conflict. Tap to resolve the problem",
      "Back Key" : "Back Key",
      "Bad URL" : "Bad URL",
      "Better Internet" : "Better Internet",
      "Bug report " : "Bug report ",
      "Check out Hola for Android!" : "Check out Hola for Android!",
      "Clear cache" : "Clear cache",
      "Clear data" : "Clear data",
      "Client ID: " : "Client ID: ",
      "Connecting..." : "Connecting...",
      "Could not start VPN service" : "Could not start VPN service",
      "Create Android VPN" : "Create Android VPN",
      "Create a VPN connection" : "Create a VPN connection",
      "Debug" : "Debug",
      "Device incompatible with Hola: " : "Device incompatible with Hola: ",
      "Download the app" : "Download the app",
      "Downloading apk" : "Downloading apk",
      "Downloading..." : "Downloading...",
      "Enable 'Unknown sources'" : "Enable 'Unknown sources'",
      "Error showing VPN Service dialog" : "Error showing VPN Service dialog",
      "Error trying to show the Android 4.0+ VPN Service dialog. This shouldn't happen as it's a standard feature of Android 4.0+, but your Android device may not support VPN auto-configuration." : "Error trying to show the Android 4.0+ VPN Service dialog. This shouldn't happen as it's a standard feature of Android 4.0+, but your Android device may not support VPN auto-configuration.",
      "FAQ" : "FAQ",
      "Failed starting VPN\nTry again in a moment" : "Failed starting VPN\nTry again in a moment",
      "Faster Internet browsing.\nLess video buffering.\nQuicker downloads." : "Faster Internet browsing.\nLess video buffering.\nQuicker downloads.",
      "Feedback for Hola on Android " : "Feedback for Hola on Android ",
      "Get started!" : "Get started!",
      "Google Play not available" : "Google Play not available",
      "Got it" : "Got it",
      "Help" : "Help",
      "Hola " : "Hola ",
      "Hola Better Internet" : "Hola Better Internet",
      "Hola Service" : "Hola Service",
      "Hola Space Manager" : "Hola Space Manager",
      "Hola VPN Service" : "Hola VPN Service",
      "Hola VPN is disconnected after reboot." : "Hola VPN is disconnected after reboot.",
      "Hola bug report: " : "Hola bug report: ",
      "Hola can't automatically configure VPN connections on your Android device." : "Hola can't automatically configure VPN connections on your Android device.",
      "Hola can't open VPN connection" : "Hola can't open VPN connection",
      "Hola failed starting VPN service\n" : "Hola failed starting VPN service\n",
      "Hola failed to open package " : "Hola failed to open package ",
      "Hola failed to open the rating page on Play\nSearch for Hola on Google Play and rate us there! " : "Hola failed to open the rating page on Play\nSearch for Hola on Google Play and rate us there! ",
      "Hola failed to open the sharing options window. " : "Hola failed to open the sharing options window. ",
      "Hola failed to run. Tap to resolve the problem" : "Hola failed to run. Tap to resolve the problem",
      "Hola is downloading" : "Hola is downloading",
      "Hola is off" : "Hola is off",
      "Hola is on!" : "Hola is on!",
      "Hola is secure and respects your privacy." : "Hola is secure and respects your privacy.",
      "Hola needs a VPN connection" : "Hola needs a VPN connection",
      "Hola speeds up my Internet and lets me access blocked sites" : "Hola speeds up my Internet and lets me access blocked sites",
      "Hola was closed by you or another app" : "Hola was closed by you or another app",
      "How to change to %1$s" : "How to change to %1$s",
      "How to free space" : "How to free space",
      "I trust this application." : "I trust this application.",
      "I'm sharing access to" : "I'm sharing access to",
      "Initializing" : "Initializing",
      "Insert SD card to enable Hola" : "Insert SD card to enable Hola",
      "Install" : "Install",
      "Install Root Checker app" : "Install Root Checker app",
      "Install failed, %1$s, can't run hola." : "Install failed, %1$s, can't run hola.",
      "Install the app" : "Install the app",
      "Installing..." : "Installing...",
      "Internet connected" : "Internet connected",
      "Learn about root access" : "Learn about root access",
      "Learn more" : "Learn more",
      "Learn more." : "Learn more.",
      "Loading Hola..." : "Loading Hola...",
      "No Internet" : "No Internet",
      "No Internet connections... go back and try again" : "No Internet connections... go back and try again",
      "Not enough free space on system partition to run Hola" : "Not enough free space on system partition to run Hola",
      "Not enough free space to run Hola" : "Not enough free space to run Hola",
      "Note: You need to do this after every device reboot" : "Note: You need to do this after every device reboot",
      "OK" : "OK",
      "On the following screen press 'Unknown sources' and then press the back key" : "On the following screen press 'Unknown sources' and then press the back key",
      "Open Play store now" : "Open Play store now",
      "Open Settings" : "Open Settings",
      "Press Start Hola, then 'I trust this app...':" : "Press Start Hola, then 'I trust this app...':",
      "Press Start Hola, then Grant Hola in Superuser:" : "Press Start Hola, then Grant Hola in Superuser:",
      "Press reload if the page doesn't load" : "Press reload if the page doesn't load",
      "Problem starting Hola" : "Problem starting Hola",
      "Problem with Hola app installation" : "Problem with Hola app installation",
      "Rate Hola" : "Rate Hola",
      "Rate on Play" : "Rate on Play",
      "Rate us not available " : "Rate us not available ",
      "Regular Acceleration" : "Regular Acceleration",
      "Remove 'Deny' on Hola in %1$s and retry" : "Remove 'Deny' on Hola in %1$s and retry",
      "Retry root access" : "Retry root access",
      "Root" : "Root",
      "Root access denied" : "Root access denied",
      "Root access or Android 4.0+ required" : "Root access or Android 4.0+ required",
      "Save Data" : "Save Data",
      "Saved" : "Saved",
      "Select Root or VPN mode" : "Select Root or VPN mode",
      "Send Feedback " : "Send Feedback ",
      "Send bug report, I'm rooted" : "Send bug report, I'm rooted",
      "Send debug info" : "Send debug info",
      "Settings" : "Settings",
      "Share" : "Share",
      "Share Hola" : "Share Hola",
      "Share Hola script" : "Share Hola script",
      "Sharing not available " : "Sharing not available ",
      "Sorry,\nthis site is blocked\nin your country." : "Sorry,\nthis site is blocked\nin your country.",
      "Start Hola on boot" : "Start Hola on boot",
      "Start Hola!" : "Start Hola!",
      "Statistics" : "Statistics",
      "Stretch your mobile data plan\nand save 20-30% over time." : "Stretch your mobile data plan\nand save 20-30% over time.",
      "Support" : "Support",
      "Surf Faster" : "Surf Faster",
      "Tap to begin" : "Tap to begin",
      "Tap to enable Hola" : "Tap to enable Hola",
      "Tap to get app from Play" : "Tap to get app from Play",
      "Tap to install" : "Tap to install",
      "Testing connection" : "Testing connection",
      "The unblocker can't run on your device" : "The unblocker can't run on your device",
      "This site can only be viewed\nfrom the United States." : "This site can only be viewed\nfrom the United States.",
      "To fix, uninstall Hola and re-install from Play." : "To fix, uninstall Hola and re-install from Play.",
      "Total data used      " : "Total data used      ",
      "Try again in a moment" : "Try again in a moment",
      "Try root mode now" : "Try root mode now",
      "Unblock Apps" : "Unblock Apps",
      "Unblocked" : "Unblocked",
      "Unblocker" : "Unblocker",
      "Unblocker not available" : "Unblocker not available",
      "Uninstall Hola for now" : "Uninstall Hola for now",
      "VPN" : "VPN",
      "Version: " : "Version: ",
      "You have a Proxy or Ad-Blocker app running, turn it off or use Hola in VPN mode" : "You have a Proxy or Ad-Blocker app running, turn it off or use Hola in VPN mode",
      "agent bytes " : "agent bytes ",
      "approved" : "approved",
      "back" : "back",
      "cancel" : "cancel",
      "disable" : "disable",
      "disabled" : "disabled",
      "enable" : "enable",
      "enabled" : "enabled",
      "failed" : "failed",
      "feedback" : "feedback",
      "home" : "home",
      "network" : "network",
      "next" : "next",
      "now" : "now",
      "on Play. " : "on Play. ",
      "pause" : "pause",
      "resume" : "resume",
      "saved bytes " : "saved bytes ",
      "share & feedback" : "share & feedback",
      "shutdown" : "shutdown",
      "skip" : "skip",
      "start" : "start",
      "started" : "started",
      "starting" : "starting",
      "stop" : "stop",
      "stopped" : "stopped",
      "stopping" : "stopping",
      "swipe to get started " : "swipe to get started ",
      "tap to select sites" : "tap to select sites",
      "total bytes " : "total bytes "
   },
   "extension" : {
      "$1 blocked?" : "$1 ব্লক?",
      "$1 unblocked" : "অবরোধমুক্ত $1",
      "(some Hola features are not available on your version)" : "(কিছু Hola বৈশিষ্ট্য আপনার সংস্করণে উপলব্ধ হয় না)",
      "Accelerator" : "বেগবর্ধক",
      "Access ALL of the Internet! Go to blocked site -> click Hola icon -> change country flag -> ENJOY!" : "ইন্টারনেটের সব অ্যাক্সেসের! ব্লক করা সাইটে যান -> ক্লিক Hola আইকন -> পরিবর্তন দেশের পতাকা -> উপভোগ করুন!",
      "Access any site from any country, free" : "বিনামূল্যে, কোন দেশ থেকে যে কোন সাইট অ্যাক্সেস",
      "Author site:" : "লেখক সাইট:",
      "Author:" : "লেখক:",
      "Enable" : "সক্ষম করা",
      "Get Hola Plus for un-interrupted, ad-free service." : "জাতিসংঘের বাধাপ্রাপ্ত, বিজ্ঞাপন মুক্ত পরিসেবার জন্য Hola প্লাস পান.",
      "Get help from engineer over skype:" : "স্কাইপ প্রকৌশলী থেকে সাহায্য পাওয়া যায়:",
      "Hola" : "Hola",
      "Hola Better Internet" : "Hola উন্নত ইন্টারনেট",
      "Hola cannot work properly because another extension is controlling your proxy settings. Please disable other extensions that you think might control your proxy settings in <a>extensions</a> (such as ad-blockers, other VPN services, etc.)." : "অন্য এক্সটেনশানের আপনার প্রক্সি সেটিংস নিয়ন্ত্রণ কারণ Hola সঠিকভাবে কাজ করতে পারবে না. আপনি <a> এক্সটেনশনগুলি </a> আপনার প্রক্সি সেটিংস (যেমন AD-ব্লকার, অন্যান্য তথ্য VPN সেবা, ইত্যাদি) নিয়ন্ত্রণ করা হতে পারে মনে করেন যে অন্য এক্সটেনশান অক্ষম করুন.",
      "Hola does not work well in Windows 8 mode. Please switch to desktop mode. Click <a>here</a> for instructions" : "Hola উইন্ডোজ 8 মোডে দুর্দান্ত কাজ করে না. ডেস্কটপ মোডে স্যুইচ করুন দয়া করে. নির্দেশাবলীর জন্য <a> এখানে </a> ক্লিক করুন",
      "Improve translation" : "অনুবাদ উন্নতি",
      "Initializing..." : "আরম্ভের ...",
      "Loading" : "বোঝাই",
      "Number of users that pressed not working" : "কাজ না করে চাপা যে ব্যবহারকারীর সংখ্যা",
      "Number of users that use this option" : "এই অপশনটি ব্যবহার করে ব্যবহারকারীর সংখ্যা",
      "OFF" : "বন্ধ",
      "ON" : "উপর",
      "Old version of Firefox. Press <a>here</a> to upgrade." : "Firefox-র পুরোনো সংস্করণ. প্রেস <a> এখানে </a> আপগ্রেড করার.",
      "Reload" : "পুনরায় বোঝাই করা",
      "Reload Hola" : "Hola পুনঃ লোড করুন",
      "Remove ads" : "বিজ্ঞাপন সরান",
      "Settings" : "সেটিংস",
      "Starting..." : "শুরু হচ্ছে ...",
      "The free version of Hola needs to be re-enabled every 4 hours and is sponsored by ads." : "Hola বিনামূল্যে সংস্করণে প্রতি 4 ঘন্টা পুনরায় সক্রিয় করা এবং বিজ্ঞাপন দ্বারা স্পন্সর করা হয় প্রয়োজন.",
      "There seems to be an error" : "একটি ত্রুটি আছে বলে মনে হয়",
      "Translate to your language" : "আপনার ভাষা থেকে অনুবাদ",
      "Try to <span>reload</span>" : "<span> পুনরায় লোড করুন </span> চেষ্টা করুন",
      "Turn on to get started" : "শুরু করার জন্য চালু করুন",
      "Unblocker" : "Unblocker",
      "Unblocker is disabled" : "Unblocker নিষ্ক্রিয় করা হয়েছে",
      "Unblocker site list" : "Unblocker সাইট তালিকা",
      "Update" : "আপডেট করুন",
      "Verify you have Internet" : "আপনি ইন্টারনেট আছে কিনা তা পরীক্ষা করুন",
      "Very old version of Chrome, <a>update</a> Chrome to use Hola" : "Chrome-এর অত্যন্ত পুরোনো সংস্করণ, <a> আপডেট করুন </a> Chrome-Hola ব্যবহার",
      "Want Hola on other devices? (Xbox, PS, Apple TV, iPhone...). Click here" : "অন্যান্য ডিভাইসের Hola চান? (মান্নান ভুঁইয়া, থানা, অ্যাপল টিভি, আইফোন ...). এখানে ক্লিক করুন",
      "back to" : "ফিরে",
      "changing..." : "পরিবর্তন ...",
      "even more..." : "এমনকি আরও অনেক কিছু ...",
      "more options..." : "more options...",
      "more..." : "আরও অনেক কিছু ...",
      "not working?" : "not working?",
      "start" : "শুরু"
   }
}
